[{"Id":"1","FirstName":"assx","LastName":"mnm","Email":"as@a.com","Phone":"017474572541","Password":"123Qay123","CreatedAt":"0001-01-01T00:00:00","PhotoPath":null},{"Id":null,"FirstName":"as","LastName":"as","Email":"ayma513@gmail.com","Phone":"017474572541","Password":"123Qay123","CreatedAt":"0001-01-01T00:00:00","PhotoPath":null},{"Id":"7a3a0fe9-e84f-404f-9af8-4ae6b32396c2","FirstName":"saxy","LastName":"saxy","Email":"mohamad513ms@gmail.com","Phone":"017474572541","Password":"123Qay123","CreatedAt":"2025-02-10T13:55:38.4564149Z","PhotoPath":null},{"Id":"a9088655-44a2-4dbf-8332-19cc22bfa8b2","FirstName":"saxy\u0633","LastName":"saxy","Email":"mohamad513ms@gmail.com","Phone":"01747457233","Password":"123Qay123","CreatedAt":"2025-02-10T13:55:40.3272725Z","PhotoPath":null},{"Id":"ceb762c3-c7ed-408f-8319-388d5161e721","FirstName":"saxy","LastName":"saxy","Email":"mohamad513ms@gmail.com","Phone":"017474572541","Password":"123Qay123","CreatedAt":"2025-02-10T13:55:41.3288112Z","PhotoPath":null},{"Id":"722824e2-d4fd-470b-bd40-46d5c01a5898","FirstName":"saxy","LastName":"saxy","Email":"mohamad513ms@gmail.com","Phone":"017474572541","Password":"123Qay123","CreatedAt":"2025-02-10T13:55:41.8480814Z","PhotoPath":null},{"Id":"d39fee2e-450e-46b9-941f-cfddc8c287c9","FirstName":"saxy","LastName":"saxy","Email":"mohamad513ms@gmail.com","Phone":"017474572541","Password":"123Qay123","CreatedAt":"2025-02-10T13:55:42.6502866Z","PhotoPath":null},{"Id":"222fdedd-f85a-4955-9090-105fb6e64485","FirstName":"saxy","LastName":"saxy","Email":"mohamad513ms@gmail.com","Phone":"017474572541","Password":"123Qay123","CreatedAt":"2025-02-10T13:55:42.9964034Z","PhotoPath":null},{"Id":"7b7a001f-001c-46ae-9a55-ef4469d1eb29","FirstName":"saxy","LastName":"saxy","Email":"mohamad513ms@gmail.com","Phone":"017474572541","Password":"123Qay123","CreatedAt":"2025-02-10T13:55:43.689603Z","PhotoPath":null},{"Id":"285b1ba3-c66b-428c-a054-b555ebb17e29","FirstName":"saxy","LastName":"saxy","Email":"mohamad513ms@gmail.com","Phone":"017474572541","Password":"123Qay123","CreatedAt":"2025-02-10T13:56:02.9849373Z","PhotoPath":null},{"Id":"631e9633-0267-411f-9697-fef116f67d9d","FirstName":"saxy","LastName":"saxy","Email":"mohamad513ms@gmail.com","Phone":"017474572541","Password":"123Qay123","CreatedAt":"2025-02-10T13:56:03.6860691Z","PhotoPath":null},{"Id":"394f90fe-600d-46fc-97e3-a9265bae2493","FirstName":"saxy","LastName":"saxy","Email":"mohamad513ms@gmail.com","Phone":"017474572541","Password":"123Qay123","CreatedAt":"2025-02-10T13:56:04.15408Z","PhotoPath":null},{"Id":"5265a704-656b-44b2-b30c-59a127dfbefe","FirstName":"saxy","LastName":"saxy","Email":"mohamad513ms@gmail.com","Phone":"017474572541","Password":"123Qay123","CreatedAt":"2025-02-10T13:56:04.3842474Z","PhotoPath":null},{"Id":"56805097-e82c-4947-8ae7-268f38bfd247","FirstName":"saxy","LastName":"saxy","Email":"mohamad513ms@gmail.com","Phone":"017474572541","Password":"123Qay123","CreatedAt":"2025-02-10T13:56:04.6147417Z","PhotoPath":null},{"Id":"49a02121-0e99-4336-b3b7-08987cba2eae","FirstName":"saxy","LastName":"saxy","Email":"mohamad513ms@gmail.com","Phone":"017474572541","Password":"123Qay123","CreatedAt":"2025-02-10T13:56:05.0761517Z","PhotoPath":null},{"Id":"0fb6c6f9-9af1-4cf1-9d45-4773ac19b6b5","FirstName":"saxy","LastName":"saxy","Email":"mohamad513ms@gmail.com","Phone":"017474572541","Password":"123Qay123","CreatedAt":"2025-02-10T13:56:13.4432874Z","PhotoPath":null},{"Id":"1979ab5c-c6d1-4bdc-932e-e1b91b4a2e80","FirstName":"asw","LastName":"sam","Email":"ayma513@gmail.com","Phone":"017474572541","Password":"$2a$11$GxCaR7ZNvncSobNGmTlIHuAr.RyUu/RSIumdKYBhA.uHjrj3TTmCW","CreatedAt":"2025-02-10T14:04:04.4990626Z","PhotoPath":null},{"Id":null,"FirstName":"photo","LastName":"photo","Email":"photo@photo.photo","Phone":"1","Password":"$2a$11$itsfSZ75McTl70HULwmVQ.tKlpZwMl2udXJSUcVGODKk74stDeMyG","CreatedAt":"0001-01-01T00:00:00","PhotoPath":"http://localhost:5270/students/photo_photo.png"},{"Id":null,"FirstName":"photo","LastName":"photo","Email":"photo@photo.photo","Phone":"photo","Password":"$2a$11$wOqGdCz3VegpOTJkPeLwV.c1iOVcqTsvIJurxlnpRjnvR7fr8S2I.","CreatedAt":"0001-01-01T00:00:00","PhotoPath":"http://localhost:5270/students/photo_photo.png"},{"Id":null,"FirstName":"photo\u0630","LastName":"photo","Email":"phot@photo.photo","Phone":"1","Password":"$2a$11$kiy59zoxNcLwgUSYlgd3DOs22xpPh6xxikw44KAgPXQdTahmkqola","CreatedAt":"0001-01-01T00:00:00","PhotoPath":"http://localhost:5270/students/photo\u0630_photo.png"},{"Id":null,"FirstName":"photo\u0630","LastName":"photo","Email":"phot@photo.photo","Phone":"1","Password":"$2a$11$.Mx5k26L9fS.33Iz.nCWH.0aTq2y4qvoIXVHddJq/VeQGmlyVd30u","CreatedAt":"0001-01-01T00:00:00","PhotoPath":"http://localhost:5270/students/photo\u0630_photo.png"},{"Id":null,"FirstName":"123123","LastName":"Smith","Email":"johndoe@skillwave.com","Phone":"01786565657","Password":"$2a$11$JuQzpjHYtUuit4x9FrruZuepcTfHmnk2ouLAj9vy.Ro04VJ85yDT6","CreatedAt":"0001-01-01T00:00:00","PhotoPath":"http://localhost:5270/students/123123_Smith.webp"},{"Id":null,"FirstName":"asdasd","LastName":"Doe","Email":"janesmith@skillwave.com","Phone":"1234567890","Password":"$2a$11$5mnEfQTYKauc3YMU/vItoufs0HJCue3lYNP.Val2LaJjPkLTmAMVq","CreatedAt":"0001-01-01T00:00:00","PhotoPath":"http://localhost:5270/students/asdasd_Doe.webp"},{"Id":null,"FirstName":"123123","LastName":"123","Email":"123@123.123","Phone":"01234567898","Password":"$2a$11$0js719GLcoqRLIVomV98ueAHIyYqVSph3tx9PTmkWtRg1jX2xSGH2","CreatedAt":"0001-01-01T00:00:00","PhotoPath":"http://localhost:5270/students/123123_123.png"}]